half_adder/full_adder.v
module full_adder(
	input A,B,Cin,
	output S,Co
);

	assign S = A^B^Cin;
	assign Co = (A & B) | (Cin & (A^B));
	
endmodule

half_adder/tb_full_adder.v
module tb_full_adder;

	reg A,B,Cin;
	wire S,Co;
	
	full_adder uut(
		.A(A),
		.B(B),
		.Cin(Cin),
		.S(S),
		.Co(Co)
	);
	initial begin 
		$dumpfile("full_adder.vcd");
		$dumpvars(0,tb_full_adder);
		
		A = 0; B = 0; Cin = 0; #10;
		A = 0; B = 0; Cin = 1; #10;
		A = 0; B = 1; Cin = 0; #10;
		A = 0; B = 1; Cin = 1; #10;
		A = 1; B = 0; Cin = 0; #10;
		A = 1; B = 0; Cin = 1; #10;
		A = 1; B = 1; Cin = 0; #10;
		A = 1; B = 1; Cin = 1; #10;
		
		$finish;
	end
endmodule

half_adder/full_adder.vcd
$date
	Wed Aug 20 16:55:51 2025
$end
$version
	Icarus Verilog
$end
$timescale
	1s
$end
$scope module tb_full_adder $end
$var wire 1 ! S $end
$var wire 1 " Co $end
$var reg 1 # A $end
$var reg 1 $ B $end
$var reg 1 % Cin $end
$scope module uut $end
$var wire 1 # A $end
$var wire 1 $ B $end
$var wire 1 % Cin $end
$var wire 1 " Co $end
$var wire 1 ! S $end
$upscope $end
$upscope $end
$enddefinitions $end
$comment Show the parameter values. $end
$dumpall
$end
#0
$dumpvars
0%
0$
0#
0"
0!
$end
#10
1!
1%
#20
0%
1$
#30
1"
0!
1%
#40
0"
1!
0%
0$
1#
#50
1"
0!
1%
#60
0%
1$
#70
1!
1%
